lilota/__init__.py
lilota/core.py
lilota/models.py
lilota/runner.py
lilota/stores.py
lilota/utils.py
lilota/db/__init__.py
lilota/db/alembic.py
lilota/db/migrations/README
lilota/db/migrations/env.py
lilota/db/migrations/script.py.mako
lilota/db/migrations/__pycache__/env.cpython-312.pyc
lilota/db/migrations/versions/95a1ff845fe1_initial_schema.py
lilota/db/migrations/versions/__pycache__/95a1ff845fe1_initial_schema.cpython-312.pyc
lilota-0.8.0.dist-info/licenses/LICENSE
sample/__init__.py
sample/lilota-sample-2.py
sample/lilota-sample.py
lilota-0.8.0.dist-info/METADATA
lilota-0.8.0.dist-info/WHEEL
lilota-0.8.0.dist-info/top_level.txt
lilota-0.8.0.dist-info/RECORD
