Metadata-Version: 2.4
Name: lilota
Version: 0.8.0
Summary: A lightweight solution for long-running tasks
Author-email: Tobias Rössler <tobiasroessler@gmail.com>
Project-URL: Homepage, https://github.com/tobiasroessler/lilota
Project-URL: Issues, https://github.com/tobiasroessler/lilota/issues
Classifier: Programming Language :: Python :: 3
Classifier: License :: OSI Approved :: MIT License
Classifier: Operating System :: OS Independent
Requires-Python: >=3.12
License-File: LICENSE
Requires-Dist: SQLAlchemy<3.0,>=2.0.45
Requires-Dist: psycopg[binary]<4.0,>=3.3.2
Requires-Dist: alembic<2.0,>=1.17.2
Provides-Extra: dev
Requires-Dist: build; extra == "dev"
Requires-Dist: twine; extra == "dev"
Dynamic: license-file
